{"hash":"5ff936bc0a5e0758bdaf4c2b971c3afa5429241d","data":{"member":{"netid":"ls797","firstName":"Laura","lastName":"Sizemore","name":"Laura Sizemore","graduation":"May 2021","major":"Computer Science","linkedin":"https://www.linkedin.com/in/laura-sizemore/","github":"https://github.com/lsizemore8","hometown":"Burke, VA","about":"I am a junior studying Computer Science in the College of Engineering and am minoring in Public Policy. I enjoy using technology to cause a positive impact in my community and beyond. In addition to software development and technical project management, I have experience in full-stack development and data analysis. When I'm not coding, I enjoy reading sci-fi and fantasy novels, playing both board and video games, going to the gym, and spending time with friends.","subteam":"Leads","otherSubteams":["researchconnect","carriage"],"website":null,"roleId":"lead","roleDescription":"Lead"}},"context":{}}