{"hash":"7586878e87e56bd18d996565511a530f12f93299","data":{"member":{"netid":"bjt84","firstName":"Bryan","lastName":"Tabor","name":"Bryan Tabor","graduation":"December 2022","major":"Computer Science","linkedin":"https://www.linkedin.com/in/bryan-tabor","github":"https://github.com/raisinrand","hometown":"Weaverville, NC","about":"I'm a freshman majoring in Computer Science. I'm interested in computer graphics and game development. In my free time, I like playing Tetris and rhythm games.","subteam":"carriage","otherSubteams":null,"website":"http://btabor.net","roleId":"developer","roleDescription":"Developer"}},"context":{}}